astro_tiptop-1.3.32.dist-info/licenses/LICENSE
tiptop/__init__.py
tiptop/_version.py
tiptop/asterismSimulation.py
tiptop/asterismSimulationHo.py
tiptop/baseSimulation.py
tiptop/nnModel.py
tiptop/tiptop.py
tiptop/tiptopCLT.py
tiptop/tiptopGUI.py
tiptop/tiptopUtils.py
tiptop/astTest/ERISast.ini
tiptop/astTest/ERISast10.ini
tiptop/astTest/ERISast100.ini
tiptop/astTest/ERISast1000.ini
tiptop/astTest/ERISastHO.ini
tiptop/astTest/ERISastHOtest.ini
tiptop/astTest/ERISastMonads.ini
tiptop/astTest/ERISastRandom.ini
tiptop/astTest/ERISastSingles1.ini
tiptop/astTest/ERISastSinglesTest.ini
tiptop/astTest/MAVISast.ini
tiptop/astTest/MAVISastGenerate.ini
tiptop/astTest/MAVISastSingles.ini
tiptop/astTest/MAVISastTriplets.ini
tiptop/astTest/rec_array10.npy
tiptop/astTest/rec_array100.npy
tiptop/astTest/rec_array100_e.npy
tiptop/astTest/rec_array10_e.npy
tiptop/data/CombinedError_Wavefront_nm.fits
tiptop/data/EELT480pp0.0803m_obs0.283_spider2023.fits
tiptop/data/ELT_M1_MORFEO_DMs_static_wfe_480px.fits
tiptop/data/ELT_M1_static_wfe_480px.fits
tiptop/data/eris_vibrations_psd.fits
tiptop/data/morfeo_windshake8ms_psd_2022_1k.fits
tiptop/data/sphere_tiptop_zeith30.0deg_psfs_wvl_550.0nm_nPSF1_seeing0.735632arcsec_L022.0m_iso2.3042962606561943arcsec.fits
tiptop/data/ini/sphere.ini
tiptop/perfTest/ERIS.ini
tiptop/perfTest/ERIS_LGS.ini
tiptop/perfTest/HARMONI_SCAO.ini
tiptop/perfTest/HarmoniLTAO_1.ini
tiptop/perfTest/HarmoniLTAO_2.ini
tiptop/perfTest/HarmoniLTAO_3.ini
tiptop/perfTest/MAVIS.ini
tiptop/perfTest/MAVIStest.ini
tiptop/perfTest/METIS.ini
tiptop/perfTest/MICADO_SCAO.ini
tiptop/perfTest/MORFEO.ini
tiptop/perfTest/MUSE_LTAO.ini
tiptop/perfTest/SOUL.ini
tiptop/perfTest/SPHERE.ini
tiptop/perfTest/dummy.ini
astro_tiptop-1.3.32.dist-info/METADATA
astro_tiptop-1.3.32.dist-info/WHEEL
astro_tiptop-1.3.32.dist-info/top_level.txt
astro_tiptop-1.3.32.dist-info/RECORD
