Metadata-Version: 2.4
Name: astro-tiptop
Version: 1.3.32
Summary: Analytical simulator for astronomical adaptive optics systems
Author-email: Fabio Rossi <fabio.rossi@inaf.it>, Guido Agapito <guido.agapito@inaf.it>
License: MIT License
Project-URL: repository, https://github.com/astro-tiptop/TIPTOP
Requires-Python: >=3.11
License-File: LICENSE
Requires-Dist: matplotlib
Requires-Dist: numpy
Requires-Dist: pyyaml
Requires-Dist: astro-p3>=1.4.10
Requires-Dist: mastsel>=1.3.12
Requires-Dist: torch>=2.1.2
Requires-Dist: torchmetrics>=1.4.0
Requires-Dist: mpl_scatter_density>=0.7
Provides-Extra: docs
Provides-Extra: gpu
Requires-Dist: mastsel[gpu]; extra == "gpu"
Provides-Extra: gui
Requires-Dist: ipywidgets; extra == "gui"
Dynamic: license-file
